667bot/__init__.py
667bot-1.0.0.dist-info/DESCRIPTION.rst
667bot-1.0.0.dist-info/METADATA
667bot-1.0.0.dist-info/RECORD
667bot-1.0.0.dist-info/WHEEL
667bot-1.0.0.dist-info/dependency_links.txt
667bot-1.0.0.dist-info/metadata.json
667bot-1.0.0.dist-info/top_level.txt
oimbot/__init__.py
