Metadata-Version: 2.0
Name: 667bot
Version: 1.0.0
Summary: Lobby bot.
Home-page: https://bot.aerozoff.com
Author: Aeroz
Author-email: UNKNOWN
License: UNKNOWN
Platform: UNKNOWN
Classifier: Programming Language :: Python :: 3
Classifier: License :: OSI Approved :: MIT License
Classifier: Operating System :: OS Independent
Requires-Dist: FortniteAPIAsync
Requires-Dist: PirxcyPinger
Requires-Dist: aiohttp
Requires-Dist: crayons
Requires-Dist: requests
Requires-Dist: sanic (==21.6.2)
